{
  "username": "bellastarey",
  "profile_url": "https://www.tiktok.com/@bellastarey",
  "avatar_url": "https://p16-common-sign.tiktokcdn-us.com/tos-useast8-avt-0068-tx2/411e31f7682b644220a5e17812c1d8d8~tplv-tiktokx-cropcenter:1080:1080.jpeg?dr=9640&refresh_token=dad40581&x-expires=1777752000&x-signature=JDiDL%2BpnCfQfVnX%2Bap3wisngmEk%3D&t=4d5b0474&ps=13740610&shp=a5d48078&shcp=81f88b70&idc=useast5",
  "content_type": "image/jpeg",
  "sha256": "6388b8b2b6d1dfd10e9f0e8322abc045d1ad2e7a822dda81e8ed8858b37e1291",
  "image_file": "avatar.jpg",
  "downloaded_at_unix": 1777581909
}