{
  "username": "skyskymartin",
  "profile_url": "https://www.tiktok.com/@skyskymartin",
  "avatar_url": "https://p19-common-sign.tiktokcdn-us.com/tos-useast8-avt-0068-tx2/9c39a61392f978a6b9dee46c9cc22318~tplv-tiktokx-cropcenter:1080:1080.jpeg?dr=9640&refresh_token=ff789917&x-expires=1777752000&x-signature=hqVNETKvPxCt0snf0sQZnMrV2Ic%3D&t=4d5b0474&ps=13740610&shp=a5d48078&shcp=81f88b70&idc=useast5",
  "content_type": "image/jpeg",
  "sha256": "425d274bdac432a0a2227ec81cd9f6fe84622e0a2d9c77394c04759b4db7a559",
  "image_file": "avatar.jpg",
  "downloaded_at_unix": 1777582063
}