{
  "username": "hayden2026.0",
  "profile_url": "https://www.tiktok.com/@hayden2026.0",
  "avatar_url": "https://p16-common-sign.tiktokcdn-us.com/tos-maliva-avt-0068/a0fd04e055d584595eb6cc056d72c442~tplv-tiktokx-cropcenter:1080:1080.jpeg?dr=9640&refresh_token=4d953d4c&x-expires=1777917600&x-signature=IqLzkbgmSLx2p3AIEEMlpwYlzJA%3D&t=4d5b0474&ps=13740610&shp=a5d48078&shcp=81f88b70&idc=useast5",
  "content_type": "image/jpeg",
  "sha256": "ae95f3ab489e09a9f05947768e31e169fb98a12c872b3ed8702099ba7c0717ab",
  "image_file": "avatar.jpg",
  "downloaded_at_unix": 1777747827
}