{
  "username": "filmtalk25",
  "profile_url": "https://www.tiktok.com/@filmtalk25",
  "avatar_url": "https://p19-common-sign.tiktokcdn-us.com/tos-useast8-avt-0068-tx2/ceb26df1da042d22e04907e98d878da8~tplv-tiktokx-cropcenter:1080:1080.jpeg?dr=9640&refresh_token=c7731ab7&x-expires=1778140800&x-signature=9PxM0jtgM8021t%2BdAtt65lLX0aI%3D&t=4d5b0474&ps=13740610&shp=a5d48078&shcp=81f88b70&idc=useast5",
  "content_type": "image/jpeg",
  "sha256": "961b5ce301bdb66246738a1eb497b3f2aac98b9137d474250f70b9fcd7fa0898",
  "image_file": "avatar.jpg",
  "downloaded_at_unix": 1777968056
}