{
  "username": "evadrazkowski",
  "profile_url": "https://www.tiktok.com/@evadrazkowski",
  "avatar_url": "https://p16-common-sign.tiktokcdn-us.com/tos-useast8-avt-0068-tx2/ec55c3850b8caa0daa112d234845d82f~tplv-tiktokx-cropcenter:1080:1080.jpeg?dr=9640&refresh_token=6a75ed5a&x-expires=1778331600&x-signature=z5U2vvF3jz1rQa5AYkAZgLELbmY%3D&t=4d5b0474&ps=13740610&shp=a5d48078&shcp=81f88b70&idc=useast5",
  "content_type": "image/jpeg",
  "sha256": "05c39caa3b6a0f135c177d4679b632528a1bcdf08aaea3349b14d2e388feecee",
  "image_file": "avatar.jpg",
  "downloaded_at_unix": 1778161974
}