{
  "username": "tatumbittick",
  "profile_url": "https://www.tiktok.com/@tatumbittick",
  "avatar_url": "https://p16-common-sign.tiktokcdn-us.com/tos-useast8-avt-0068-tx2/cf44be022ad3bbfa8faf41b84030e423~tplv-tiktokx-cropcenter:1080:1080.jpeg?dr=9640&refresh_token=12acd7bd&x-expires=1778637600&x-signature=ASd0ZbsiJ7qoi1DxKmRGsSu9j1A%3D&t=4d5b0474&ps=13740610&shp=a5d48078&shcp=81f88b70&idc=useast5",
  "content_type": "image/jpeg",
  "sha256": "cdd7e0540b06e6605f2ad51fcfcc3857143a078fa686c9949839bc483c4eefca",
  "image_file": "avatar.jpg",
  "downloaded_at_unix": 1778467172
}