{
  "username": "vanesa.fali",
  "profile_url": "https://www.tiktok.com/@vanesa.fali",
  "avatar_url": "https://p16-common-sign.tiktokcdn-us.com/tos-useast5-avt-0068-tx/7322675854402666542~tplv-tiktokx-cropcenter:1080:1080.jpeg?dr=9640&refresh_token=71a00bb5&x-expires=1778572800&x-signature=VGLx8guXPeVNC3NM%2BbkTV83NHoA%3D&t=4d5b0474&ps=13740610&shp=a5d48078&shcp=81f88b70&idc=useast8",
  "content_type": "image/jpeg",
  "sha256": "0897b5fe27e176637509514049ed15b962b2e29ac0e2e0f6af96825d05efc30b",
  "image_file": "avatar.jpg",
  "downloaded_at_unix": 1778400347
}