{
  "username": "4kilh4",
  "profile_url": "https://www.tiktok.com/@4kilh4",
  "avatar_url": "https://p16-common-sign.tiktokcdn-us.com/tos-useast8-avt-0068-tx2/017ac1873b2a23863451be1099d305b1~tplv-tiktokx-cropcenter:1080:1080.jpeg?dr=9640&refresh_token=0a733a1a&x-expires=1777752000&x-signature=JX2WNLF7hDEOBbma2kH%2BsGclRKY%3D&t=4d5b0474&ps=13740610&shp=a5d48078&shcp=81f88b70&idc=useast5",
  "content_type": "image/jpeg",
  "sha256": "7abf244bbbddce4aea5271a96fc05747af576465dadbc96ea3b04a6c50f526c7",
  "image_file": "avatar.jpg",
  "downloaded_at_unix": 1777581890
}